brainsight/__init__.py
brainsight/modules/__init__.py
brainsight/modules/base_module.py
brainsight/modules/defaults.py
brainsight/modules/lfp.py
brainsight/modules/periodogram.py
brainsight/modules/spectrogram.py
brainsight/modules/utils.py
brainsight/types/__init__.py
brainsight/types/dataset.py
brainsight/types/signal.py
brainsight/types/utils.py
brainsight/utils/mappings.py
brainsight-0.2.0.dist-info/METADATA
brainsight-0.2.0.dist-info/WHEEL
brainsight-0.2.0.dist-info/RECORD
